{
    "data": [
        {
            "attributes": {
                "arrival_time": null,
                "departure_time": "2023-11-12T18:48:00-05:00",
                "direction_id": 0,
                "schedule_relationship": null,
                "status": null,
                "stop_sequence": 1
            },
            "id": "prediction-58791311-49001-1",
            "relationships": {
                "route": {
                    "data": {
                        "id": "749",
                        "type": "route"
                    }
                },
                "stop": {
                    "data": {
                        "id": "49001",
                        "type": "stop"
                    }
                },
                "trip": {
                    "data": {
                        "id": "58791311",
                        "type": "trip"
                    }
                },
                "vehicle": {
                    "data": {
                        "id": "y1288",
                        "type": "vehicle"
                    }
                }
            },
            "type": "prediction"
        },
        {
            "attributes": {
                "arrival_time": null,
                "departure_time": "2023-11-12T18:57:00-05:00",
                "direction_id": 0,
                "schedule_relationship": null,
                "status": null,
                "stop_sequence": 1
            },
            "id": "prediction-58791312-49001-1",
            "relationships": {
                "route": {
                    "data": {
                        "id": "749",
                        "type": "route"
                    }
                },
                "stop": {
                    "data": {
                        "id": "49001",
                        "type": "stop"
                    }
                },
                "trip": {
                    "data": {
                        "id": "58791312",
                        "type": "trip"
                    }
                },
                "vehicle": {
                    "data": {
                        "id": "y1284",
                        "type": "vehicle"
                    }
                }
            },
            "type": "prediction"
        },
        {
            "attributes": {
                "arrival_time": null,
                "departure_time": "2023-11-12T19:06:00-05:00",
                "direction_id": 0,
                "schedule_relationship": null,
                "status": null,
                "stop_sequence": 1
            },
            "id": "prediction-58791313-49001-1",
            "relationships": {
                "route": {
                    "data": {
                        "id": "749",
                        "type": "route"
                    }
                },
                "stop": {
                    "data": {
                        "id": "49001",
                        "type": "stop"
                    }
                },
                "trip": {
                    "data": {
                        "id": "58791313",
                        "type": "trip"
                    }
                },
                "vehicle": {
                    "data": {
                        "id": "y1274",
                        "type": "vehicle"
                    }
                }
            },
            "type": "prediction"
        },
        {
            "attributes": {
                "arrival_time": null,
                "departure_time": "2023-11-12T19:15:00-05:00",
                "direction_id": 0,
                "schedule_relationship": null,
                "status": null,
                "stop_sequence": 1
            },
            "id": "prediction-58791314-49001-1",
            "relationships": {
                "route": {
                    "data": {
                        "id": "749",
                        "type": "route"
                    }
                },
                "stop": {
                    "data": {
                        "id": "49001",
                        "type": "stop"
                    }
                },
                "trip": {
                    "data": {
                        "id": "58791314",
                        "type": "trip"
                    }
                },
                "vehicle": {
                    "data": {
                        "id": "y1278",
                        "type": "vehicle"
                    }
                }
            },
            "type": "prediction"
        },
        {
            "attributes": {
                "arrival_time": null,
                "departure_time": "2023-11-12T19:24:00-05:00",
                "direction_id": 0,
                "schedule_relationship": null,
                "status": null,
                "stop_sequence": 1
            },
            "id": "prediction-58791315-49001-1",
            "relationships": {
                "route": {
                    "data": {
                        "id": "749",
                        "type": "route"
                    }
                },
                "stop": {
                    "data": {
                        "id": "49001",
                        "type": "stop"
                    }
                },
                "trip": {
                    "data": {
                        "id": "58791315",
                        "type": "trip"
                    }
                },
                "vehicle": {
                    "data": {
                        "id": "y1277",
                        "type": "vehicle"
                    }
                }
            },
            "type": "prediction"
        },
        {
            "attributes": {
                "arrival_time": null,
                "departure_time": "2023-11-12T19:33:00-05:00",
                "direction_id": 0,
                "schedule_relationship": null,
                "status": null,
                "stop_sequence": 1
            },
            "id": "prediction-58791316-49001-1",
            "relationships": {
                "route": {
                    "data": {
                        "id": "749",
                        "type": "route"
                    }
                },
                "stop": {
                    "data": {
                        "id": "49001",
                        "type": "stop"
                    }
                },
                "trip": {
                    "data": {
                        "id": "58791316",
                        "type": "trip"
                    }
                },
                "vehicle": {
                    "data": {
                        "id": "y1288",
                        "type": "vehicle"
                    }
                }
            },
            "type": "prediction"
        },
        {
            "attributes": {
                "arrival_time": null,
                "departure_time": "2023-11-12T19:42:00-05:00",
                "direction_id": 0,
                "schedule_relationship": null,
                "status": null,
                "stop_sequence": 1
            },
            "id": "prediction-58791317-49001-1",
            "relationships": {
                "route": {
                    "data": {
                        "id": "749",
                        "type": "route"
                    }
                },
                "stop": {
                    "data": {
                        "id": "49001",
                        "type": "stop"
                    }
                },
                "trip": {
                    "data": {
                        "id": "58791317",
                        "type": "trip"
                    }
                },
                "vehicle": {
                    "data": null
                }
            },
            "type": "prediction"
        },
        {
            "attributes": {
                "arrival_time": "2023-11-12T18:46:54-05:00",
                "departure_time": null,
                "direction_id": 1,
                "schedule_relationship": null,
                "status": null,
                "stop_sequence": 12
            },
            "id": "prediction-58791270-49001-12",
            "relationships": {
                "route": {
                    "data": {
                        "id": "749",
                        "type": "route"
                    }
                },
                "stop": {
                    "data": {
                        "id": "49001",
                        "type": "stop"
                    }
                },
                "trip": {
                    "data": {
                        "id": "58791270",
                        "type": "trip"
                    }
                },
                "vehicle": {
                    "data": {
                        "id": "y1284",
                        "type": "vehicle"
                    }
                }
            },
            "type": "prediction"
        },
        {
            "attributes": {
                "arrival_time": "2023-11-12T18:59:32-05:00",
                "departure_time": null,
                "direction_id": 1,
                "schedule_relationship": null,
                "status": null,
                "stop_sequence": 12
            },
            "id": "prediction-58791271-49001-12",
            "relationships": {
                "route": {
                    "data": {
                        "id": "749",
                        "type": "route"
                    }
                },
                "stop": {
                    "data": {
                        "id": "49001",
                        "type": "stop"
                    }
                },
                "trip": {
                    "data": {
                        "id": "58791271",
                        "type": "trip"
                    }
                },
                "vehicle": {
                    "data": {
                        "id": "y1274",
                        "type": "vehicle"
                    }
                }
            },
            "type": "prediction"
        },
        {
            "attributes": {
                "arrival_time": "2023-11-12T19:10:58-05:00",
                "departure_time": null,
                "direction_id": 1,
                "schedule_relationship": null,
                "status": null,
                "stop_sequence": 12
            },
            "id": "prediction-58791272-49001-12",
            "relationships": {
                "route": {
                    "data": {
                        "id": "749",
                        "type": "route"
                    }
                },
                "stop": {
                    "data": {
                        "id": "49001",
                        "type": "stop"
                    }
                },
                "trip": {
                    "data": {
                        "id": "58791272",
                        "type": "trip"
                    }
                },
                "vehicle": {
                    "data": {
                        "id": "y1278",
                        "type": "vehicle"
                    }
                }
            },
            "type": "prediction"
        },
        {
            "attributes": {
                "arrival_time": "2023-11-12T19:14:08-05:00",
                "departure_time": null,
                "direction_id": 1,
                "schedule_relationship": null,
                "status": null,
                "stop_sequence": 12
            },
            "id": "prediction-58791273-49001-12",
            "relationships": {
                "route": {
                    "data": {
                        "id": "749",
                        "type": "route"
                    }
                },
                "stop": {
                    "data": {
                        "id": "49001",
                        "type": "stop"
                    }
                },
                "trip": {
                    "data": {
                        "id": "58791273",
                        "type": "trip"
                    }
                },
                "vehicle": {
                    "data": {
                        "id": "y1277",
                        "type": "vehicle"
                    }
                }
            },
            "type": "prediction"
        },
        {
            "attributes": {
                "arrival_time": "2023-11-12T19:26:03-05:00",
                "departure_time": null,
                "direction_id": 1,
                "schedule_relationship": null,
                "status": null,
                "stop_sequence": 12
            },
            "id": "prediction-58791274-49001-12",
            "relationships": {
                "route": {
                    "data": {
                        "id": "749",
                        "type": "route"
                    }
                },
                "stop": {
                    "data": {
                        "id": "49001",
                        "type": "stop"
                    }
                },
                "trip": {
                    "data": {
                        "id": "58791274",
                        "type": "trip"
                    }
                },
                "vehicle": {
                    "data": {
                        "id": "y1288",
                        "type": "vehicle"
                    }
                }
            },
            "type": "prediction"
        },
        {
            "attributes": {
                "arrival_time": "2023-11-12T19:31:24-05:00",
                "departure_time": null,
                "direction_id": 1,
                "schedule_relationship": null,
                "status": null,
                "stop_sequence": 12
            },
            "id": "prediction-58791275-49001-12",
            "relationships": {
                "route": {
                    "data": {
                        "id": "749",
                        "type": "route"
                    }
                },
                "stop": {
                    "data": {
                        "id": "49001",
                        "type": "stop"
                    }
                },
                "trip": {
                    "data": {
                        "id": "58791275",
                        "type": "trip"
                    }
                },
                "vehicle": {
                    "data": null
                }
            },
            "type": "prediction"
        },
        {
            "attributes": {
                "arrival_time": "2023-11-12T19:42:42-05:00",
                "departure_time": null,
                "direction_id": 1,
                "schedule_relationship": null,
                "status": null,
                "stop_sequence": 12
            },
            "id": "prediction-58791276-49001-12",
            "relationships": {
                "route": {
                    "data": {
                        "id": "749",
                        "type": "route"
                    }
                },
                "stop": {
                    "data": {
                        "id": "49001",
                        "type": "stop"
                    }
                },
                "trip": {
                    "data": {
                        "id": "58791276",
                        "type": "trip"
                    }
                },
                "vehicle": {
                    "data": {
                        "id": "y1274",
                        "type": "vehicle"
                    }
                }
            },
            "type": "prediction"
        },
        {
            "attributes": {
                "arrival_time": "2023-11-12T19:51:15-05:00",
                "departure_time": null,
                "direction_id": 1,
                "schedule_relationship": null,
                "status": null,
                "stop_sequence": 12
            },
            "id": "prediction-58791277-49001-12",
            "relationships": {
                "route": {
                    "data": {
                        "id": "749",
                        "type": "route"
                    }
                },
                "stop": {
                    "data": {
                        "id": "49001",
                        "type": "stop"
                    }
                },
                "trip": {
                    "data": {
                        "id": "58791277",
                        "type": "trip"
                    }
                },
                "vehicle": {
                    "data": null
                }
            },
            "type": "prediction"
        }
    ],
    "jsonapi": {
        "version": "1.0"
    }
}